trust_constr/__init__.py
trust_constr/_constraints.py
trust_constr/_differentiable_functions.py
trust_constr/_hessian_update_strategy.py
trust_constr/_minimize.py
trust_constr/_numdiff.py
trust_constr/interface.py
trust_constr/optimize.py
trust_constr/sputils.py
trust_constr/_trustregion_constr/__init__.py
trust_constr/_trustregion_constr/canonical_constraint.py
trust_constr/_trustregion_constr/equality_constrained_sqp.py
trust_constr/_trustregion_constr/minimize_trustregion_constr.py
trust_constr/_trustregion_constr/projections.py
trust_constr/_trustregion_constr/qp_subproblem.py
trust_constr/_trustregion_constr/report.py
trust_constr/_trustregion_constr/tr_interior_point.py
trust_constr-1.0.0.dist-info/LICENSE.txt
trust_constr-1.0.0.dist-info/METADATA
trust_constr-1.0.0.dist-info/WHEEL
trust_constr-1.0.0.dist-info/top_level.txt
trust_constr-1.0.0.dist-info/RECORD
