Metadata-Version: 2.1
Name: trust-constr
Version: 1.0.0
Summary: trust-constr optimization algorithm from the SciPy project.
Home-page: https://github.com/mgreminger/trust-constr
License: UNKNOWN
Platform: UNKNOWN
Classifier: Programming Language :: Python :: 3
Classifier: License :: OSI Approved :: BSD License
Classifier: Operating System :: OS Independent
Requires-Python: >=3.7
Requires-Dist: numpy (>=1.16.5)
